LICENSE
specio/__init__.py
specio/common/__init__.py
specio/common/colorimeters.py
specio/common/spectrometers.py
specio/common/utility.py
specio/device_implementations/__init__.py
specio/device_implementations/colorimetry_research.py
specio/device_implementations/konica_minolta.py
specio/scripts/__init__.py
specio/scripts/csmf_anonymize.py
specio/scripts/csmf_doctor.py
specio/scripts/tests/test_csmf_anonymize.py
specio/serialization/__init__.py
specio/serialization/csmf.py
specio/serialization/measurements.py
specio/serialization/protobuf/__init__.py
specio/serialization/protobuf/common.proto
specio/serialization/protobuf/common_pb2.py
specio/serialization/protobuf/common_pb2.pyi
specio/serialization/protobuf/measurements.proto
specio/serialization/protobuf/measurements_pb2.py
specio/serialization/protobuf/measurements_pb2.pyi
specio/serialization/spectral.py
specio/serialization/tests/__init__.py
specio/serialization/tests/data/1ba5c5f8.csmf
specio/serialization/tests/test_csmf.py
specio/serialization/tests/test_measurements.py
colour_specio-0.4.1.post0.dist-info/AUTHORS.md
colour_specio-0.4.1.post0.dist-info/LICENSE
colour_specio-0.4.1.post0.dist-info/METADATA
colour_specio-0.4.1.post0.dist-info/WHEEL
colour_specio-0.4.1.post0.dist-info/entry_points.txt
colour_specio-0.4.1.post0.dist-info/RECORD
